[
  {
    "line": 1,
    "elements": [
      {
        "line": 3,
        "name": "To validate the login by using valid username and valid password",
        "description": "",
        "id": "to-validate-the-logoin-functionality-of-facebook-application;to-validate-the-login-by-using-valid-username-and-valid-password",
        "type": "scenario",
        "keyword": "Scenario",
        "steps": [
          {
            "result": {
              "duration": 233800,
              "status": "skipped"
            },
            "line": 5,
            "name": "User have to enter the facebook application through chrome browser",
            "match": {
              "location": "StepDefinition.user_have_to_enter_the_facebook_application_through_chrome_browser()"
            },
            "keyword": "Given "
          },
          {
            "result": {
              "duration": 5100,
              "status": "skipped"
            },
            "line": 7,
            "name": "User have to enter the valid username and valid password",
            "match": {
              "location": "StepDefinition.user_have_to_enter_the_valid_username_and_valid_password()"
            },
            "keyword": "When "
          },
          {
            "result": {
              "duration": 3300,
              "status": "skipped"
            },
            "line": 9,
            "name": "User have to click the login button",
            "match": {
              "location": "StepDefinition.user_have_to_click_the_login_button()"
            },
            "keyword": "And "
          },
          {
            "result": {
              "duration": 3300,
              "status": "skipped"
            },
            "line": 11,
            "name": "User reach the valid or invalid credential page",
            "match": {
              "location": "StepDefinition.user_reach_the_valid_or_invalid_credential_page()"
            },
            "keyword": "Then "
          }
        ]
      }
    ],
    "name": "To validate the logoin functionality of facebook application",
    "description": "",
    "id": "to-validate-the-logoin-functionality-of-facebook-application",
    "keyword": "Feature",
    "uri": "D:/eclipse/CucumberClass/src/test/resources/Feature/login.feature",
    "tags": []
  }
]